aspose_compressor/__init__.py
aspose_compressor/aspose_compressor.py
aspose_compressor-0.0.4.dist-info/LICENSE
aspose_compressor-0.0.4.dist-info/METADATA
aspose_compressor-0.0.4.dist-info/WHEEL
aspose_compressor-0.0.4.dist-info/top_level.txt
aspose_compressor-0.0.4.dist-info/RECORD
